modelmetry/__init__.py
modelmetry/sdk.py
modelmetry/version.py
modelmetry/guardrails/client.py
modelmetry/guardrails/response.py
modelmetry/guardrails/test/guardrails_client_test.py
modelmetry/observability/__init__.py
modelmetry/observability/client.py
modelmetry/observability/event.py
modelmetry/observability/finding.py
modelmetry/observability/ingest.py
modelmetry/observability/span.py
modelmetry/observability/trace.py
modelmetry/observability/test/client_test.py
modelmetry/observability/test/completion_span_test.py
modelmetry/observability/test/event_test.py
modelmetry/observability/test/finding_test.py
modelmetry/observability/test/ingest_test.py
modelmetry/observability/test/retrieval_span_test.py
modelmetry/observability/test/span_test.py
modelmetry/observability/test/trace_test.py
modelmetry/openapi/__init__.py
modelmetry/openapi/client.py
modelmetry/openapi/errors.py
modelmetry/openapi/py.typed
modelmetry/openapi/types.py
modelmetry/openapi/api/__init__.py
modelmetry/openapi/api/default/__init__.py
modelmetry/openapi/api/default/check_payload.py
modelmetry/openapi/api/default/evaluate.py
modelmetry/openapi/api/default/ingest_signals_v1.py
modelmetry/openapi/models/__init__.py
modelmetry/openapi/models/assessment.py
modelmetry/openapi/models/assessment_action.py
modelmetry/openapi/models/assistant_message.py
modelmetry/openapi/models/assistant_message_role.py
modelmetry/openapi/models/azure_prompt_shields_v1_config.py
modelmetry/openapi/models/check_payload_request_body.py
modelmetry/openapi/models/completion_family_data.py
modelmetry/openapi/models/completion_payload.py
modelmetry/openapi/models/completion_payload_options.py
modelmetry/openapi/models/cost.py
modelmetry/openapi/models/create_event_params.py
modelmetry/openapi/models/create_event_params_metadata.py
modelmetry/openapi/models/create_finding_params.py
modelmetry/openapi/models/create_finding_params_metadata.py
modelmetry/openapi/models/create_finding_params_source.py
modelmetry_sdk-1.0.0.dist-info/LICENSE
modelmetry_sdk-1.0.0.dist-info/METADATA
modelmetry_sdk-1.0.0.dist-info/WHEEL
modelmetry_sdk-1.0.0.dist-info/top_level.txt
modelmetry_sdk-1.0.0.dist-info/RECORD
