Metadata-Version: 2.1
Name: modelmetry-sdk
Version: 1.0.0
Summary: Modelmetry SDK for Python applications.
Author-email: Modelemtry <support@modelmetry.com>
License: Apache License
Project-URL: GitHub, https://github.com/modelmetry/modelmetry-sdk-python
Project-URL: Homepage, https://modelmetry.com
Keywords: llm,monitoring,guardrails,tracing,observability,modelmetry
Classifier: Topic :: Software Development :: Libraries
Classifier: Topic :: Software Development :: Libraries :: Python Modules
Classifier: Topic :: Scientific/Engineering :: Artificial Intelligence
Requires-Python: >=3.0
License-File: LICENSE
Requires-Dist: urllib3>=1.25.3
Requires-Dist: python-dateutil>=2.9.0
Requires-Dist: typing-extensions>=4.12.2
Requires-Dist: devtools>=0.12.2
Requires-Dist: python-dotenv>=1.0.1
Requires-Dist: pytest>=8.2.2
Requires-Dist: httpx>=0.28.1
Requires-Dist: attrs>=21.3.0
Requires-Dist: python-dateutil>=2.8.0
